{
  "jsonData" : [
    {
    "banner" : "INCMV_Awards_2022_and_CFO_Vision_2022_cropped.gif",
    "tittle" : "INCinema | Lingayen, Pangasinan | 2022 ",
    "subTittle" : "",
    "subTittleColor" : "red",
    "subTittleType" : "text",
    "image" : "INC-Central-Temple-2.jpg",
    "link" : "https://www.youtube.com", 
    "different_link_per_data" : false,
    "different_img_per_data" : true,
    "redirectPage": true,
    "page" : "watch2",
    "single_gtag":"",
    "single_gtag_id" :"",    
    "allow_popup_option":true,
    "popup_option":[  
      { 
        "page" : "watch2.html", 
        "subTittle" : "Youtube",
        "subTittleIcon" : "youtube",
        "subTittleColor" : "red",
        "subTittleType" : "icon",
        "redirect_text":"Sending view from youtube",
        "link" : "https://youtu.be/yA5kpXCJgJg?t=1",
        "gtag":"https://www.googletagmanager.com/gtag/js?id=G-TF4V9TTPS1",
        "gtag_id" :"G-TF4V9TTPS1"  
      },
      { 
        "page" : "watch.html", 
        "subTittle" : "Views",
        "subTittleIcon" : "react",
        "subTittleColor" : "#1892b8",
        "subTittleType" : "icon",
        "redirect_text":"Sending view from facebook",
        "link" : "index.html",
        "gtag":"",
        "gtag_id" :""  
      }

    ],

    "redirect_text":"Sending view from facebook",
    "first_header_color":"#fff",
    "first_header_title":"Local",
    "viewData" : [
       
      {"lokal":"Aguilar",            "duration":"25:0",  "link":"", "image":"22.jpg",        "views":  97.72003645                        },
      {"lokal":"Alintaya",           "duration":"25:0",  "link":"", "image":"22.jpg",        "views":  204.920375                        },
      {"lokal":"Angio",              "duration":"25:0",  "link":"", "image":"22.jpg",        "views":  320.1425075                        },
      {"lokal":"Away",               "duration":"25:0",  "link":"", "image":"22.jpg",        "views":  288.7845853                },
      {"lokal":"Baay Ext",           "duration":"25:0",  "link":"", "image":"22.jpg",        "views":  18.23135008                      },
      {"lokal":"Bacabac",            "duration":"25:0",  "link":"", "image":"22.jpg",        "views":  452.1374821                       },
      {"lokal":"Balococ",            "duration":"25:0",  "link":"", "image":"22.jpg",        "views":  160.4358807                 },
      {"lokal":"Baloling",           "duration":"25:0",  "link":"", "image":"22.jpg",        "views":  118.1391485                        },
      {"lokal":"Banaybayan Ext",     "duration":"25:0",  "link":"", "image":"22.jpg",        "views":  804.3671657          }, 
      {"lokal":"Bateng",             "duration":"25:0",  "link":"", "image":"22.jpg",        "views":  349.3126676                }, 
      {"lokal":"Binday",             "duration":"25:0",  "link":"", "image":"22.jpg",        "views":  141.4752767                             }, 
      {"lokal":"Binmaley",           "duration":"25:0",  "link":"", "image":"22.jpg",        "views":  824.0570238                            }, 
      {"lokal":"Bisbisocol",         "duration":"25:0",  "link":"", "image":"22.jpg",        "views":  184.5012629                     }, 
      {"lokal":"Bolo",               "duration":"25:0",  "link":"", "image":"22.jpg",        "views":  26.25314412                        }, 
      {"lokal":"Bonuan",             "duration":"25:0",  "link":"", "image":"22.jpg",        "views":  1329.430048                                }, 
      {"lokal":"Bugallon",           "duration":"25:0",  "link":"", "image":"22.jpg",        "views":  170.6454368                     }, 
      {"lokal":"Calasiao",           "duration":"25:0",  "link":"", "image":"22.jpg",        "views":  102.0955605                      }, 
      {"lokal":"Calit",              "duration":"25:0",  "link":"", "image":"22.jpg",        "views":  136.3704986                       }, 
      {"lokal":"Calmay",             "duration":"25:0",  "link":"", "image":"22.jpg",        "views":  84.59346439                        }, 
      {"lokal":"Carael",             "duration":"25:0",  "link":"", "image":"22.jpg",        "views":  2295.691603                         }, 
      {"lokal":"Colisao",            "duration":"25:0",  "link":"", "image":"22.jpg",        "views":  14.58508007                      }, 
      {"lokal":"Dagupan City",       "duration":"25:0",  "link":"", "image":"22.jpg",        "views":  709.5641453                             }, 
      {"lokal":"David",              "duration":"25:0",  "link":"", "image":"22.jpg",        "views":  317.9547455                               }, 
      {"lokal":"Domalandan",         "duration":"25:0",  "link":"", "image":"22.jpg",        "views":  100.6370525                       }, 
      {"lokal":"Dulag",              "duration":"25:0",  "link":"", "image":"22.jpg",        "views":  198.3570889                        }, 
      {"lokal":"Garcia",             "duration":"25:0",  "link":"", "image":"22.jpg",        "views":  594.3420128                                }, 
      {"lokal":"Hacienda",           "duration":"25:0",  "link":"", "image":"22.jpg",        "views":  103.5540685                }, 
      {"lokal":"Haway",              "duration":"25:0",  "link":"", "image":"22.jpg",        "views":  34.27493816                       }, 
      {"lokal":"Inmalog",            "duration":"25:0",  "link":"", "image":"22.jpg",        "views":  311.3914594                        }, 
      {"lokal":"Laguit Centro",      "duration":"25:0",  "link":"", "image":"22.jpg",        "views":  12843.62151                                         }, 
      {"lokal":"Leet",               "duration":"25:0",  "link":"", "image":"22.jpg",        "views":  102.8248145                     }, 
      {"lokal":"Lingayen",           "duration":"25:0",  "link":"", "image":"22.jpg",        "views":  139.2875146                               }, 
      {"lokal":"Lobong",             "duration":"25:0",  "link":"", "image":"22.jpg",        "views":  129.0779586                               },
      {"lokal":"Longos, San Fabian", "duration":"25:0",  "link":"", "image":"22.jpg",        "views":  73.65465434                               },
      {"lokal":"Longos, Calasiao",   "duration":"25:0",  "link":"", "image":"22.jpg",        "views":  0                     },
      {"lokal":"Luyan",              "duration":"25:0",  "link":"", "image":"22.jpg",        "views":  110.8466085                         }, 
      {"lokal":"Maambal",            "duration":"25:0",  "link":"", "image":"22.jpg",        "views":  235.5490431                    }, 
      {"lokal":"Maasin Ext",         "duration":"25:0",  "link":"", "image":"22.jpg",        "views":  579.7569327                     },
      {"lokal":"Mabilao",            "duration":"25:0",  "link":"", "image":"22.jpg",        "views":  185.9597709                        },
      {"lokal":"Magtaking",          "duration":"25:0",  "link":"", "image":"22.jpg",        "views":  126.8901966                        },
      {"lokal":"Malindog Ext",       "duration":"25:0",  "link":"", "image":"22.jpg",        "views":  13.12657206                     },
      {"lokal":"Mamalingling",       "duration":"25:0",  "link":"", "image":"22.jpg",        "views":  102.0955605                        }, 
      {"lokal":"Manaoag",            "duration":"25:0",  "link":"", "image":"22.jpg",        "views":  212.212915                             }, 
      {"lokal":"Manaoag Dos",        "duration":"25:0",  "link":"", "image":"22.jpg",        "views":  58.34032027                       }, 
      {"lokal":"Mangaldan",          "duration":"25:0",  "link":"", "image":"22.jpg",        "views":  1008.558287                               }, 
      {"lokal":"Mapandan",           "duration":"25:0",  "link":"", "image":"22.jpg",        "views":  83.86421039                       }, 
      {"lokal":"Matalava",           "duration":"25:0",  "link":"", "image":"22.jpg",        "views":  887.5021221                                }, 
      {"lokal":"Ninoy",              "duration":"25:0",  "link":"", "image":"22.jpg",        "views":  888.9606301                       }, 
      {"lokal":"Palua Ext",          "duration":"25:0",  "link":"", "image":"22.jpg",        "views":  5487.636375                                    }, 
      {"lokal":"Pangapisan",         "duration":"25:0",  "link":"", "image":"22.jpg",        "views":  78.03017836                       }, 
      {"lokal":"Pugaro",             "duration":"25:0",  "link":"", "image":"22.jpg",        "views":  533.0846765                        }, 
      {"lokal":"Quetegan",           "duration":"25:0",  "link":"", "image":"22.jpg",        "views":  381.3998438                                 }, 
      {"lokal":"Rosario",            "duration":"25:0",  "link":"", "image":"22.jpg",        "views":  179.3964848                      }, 
      {"lokal":"Salomague",          "duration":"25:0",  "link":"", "image":"22.jpg",        "views":  13138.24012                                      }, 
      {"lokal":"San Fabian",         "duration":"25:0",  "link":"", "image":"22.jpg",        "views":  1085.859211                               }, 
      {"lokal":"San Jacinto",        "duration":"25:0",  "link":"", "image":"22.jpg",        "views":  6119.170342                                      }, 
      {"lokal":"Talibaew Ext",       "duration":"25:0",  "link":"", "image":"22.jpg",        "views":  373.3780497             }, 
      {"lokal":"Tulong",             "duration":"25:0",  "link":"", "image":"22.jpg",        "views":  361.7099857              }, 

  
      
      {"lokal":" ",         "divider":true , "divider_title":"Top Viewer", "color":"#38e884" , "bg":"#232129"},
        
      {"lokal":"#1 🥇 Salomague",         "duration":"25:0",  "link":"", "image":"22.jpg",        "views":  0},
      {"lokal":"#2 🥈 Laguit Centro",             "duration":"25:0",  "link":"", "image":"22.jpg",        "views":  0},
      {"lokal":"#3 🥉 San Jacinto",        "duration":"25:0",  "link":"", "image":"22.jpg",        "views":  0}
      
      ] 
    } 
      

  ]
}

 
